{
  "version": 1,
  "generated_at": "2026-04-10T11:30:15.210Z",
  "repo": {
    "name": "torque-ai",
    "working_directory": "C:\\Users\\<os-user>\\Projects\\torque-public",
    "previous_sha": "e471b2b19cd13a543feb4ec571ccb499a9b91b9c",
    "current_sha": "e471b2b19cd13a543feb4ec571ccb499a9b91b9c",
    "study_profile_id": "torque-control-plane"
  },
  "run": {
    "mode": "up-to-date",
    "manual_run_now": false,
    "force_refresh": false,
    "batch_count": 0,
    "schedule_id": "a24a26fa-abbb-4d10-bfa9-76512a4bc11c",
    "schedule_name": "codebase-study:torque-public",
    "schedule_run_id": "4d1a8c9d-1984-41f1-ac9f-69211d7c28c3",
    "wrapper_task_id": "47d52957-e085-4592-a9b4-07e5489fe1e9"
  },
  "coverage_delta": {
    "tracked_files": {
      "previous": 1533,
      "current": 1533,
      "delta": 0
    },
    "indexed_modules": {
      "previous": 1533,
      "current": 1533,
      "delta": 0
    },
    "pending_files": {
      "previous": 0,
      "current": 0,
      "delta": 0
    }
  },
  "significance": {
    "level": "none",
    "score": 0,
    "reasons": []
  },
  "changed_files": {
    "repo_delta": [],
    "processed": [],
    "removed": []
  },
  "changed_subsystems": [],
  "affected_flows": [],
  "invariant_hits": [],
  "failure_mode_hits": [],
  "hotspot_changes": {
    "entered": [],
    "exited": [],
    "touched": []
  },
  "proposals": {
    "policy": {
      "allowed": false,
      "reason": "submission_disabled",
      "threshold_level": "moderate",
      "threshold_score": 18,
      "suppressed_count": 0
    },
    "suggested": [],
    "submitted": [],
    "errors": []
  }
}